palindrome_checker/__init__.py
palindrome_checker/phrase.py
palindrome_checker-0.0.2.dist-info/METADATA
palindrome_checker-0.0.2.dist-info/WHEEL
palindrome_checker-0.0.2.dist-info/licenses/LICENSE
palindrome_checker-0.0.2.dist-info/RECORD
